friskby/__init__.py
friskby/device_config.py
friskby/friskby_dao.py
friskby/friskby_manager.py
friskby/friskby_sampler.py
friskby/friskby_submitter.py
friskby/os_release.py
friskby/ts.py
friskby/sensors/__init__.py
friskby/sensors/sds011.py
friskby-0.72.2.dist-info/top_level.txt
friskby-0.72.2.dist-info/METADATA
friskby-0.72.2.dist-info/DESCRIPTION.rst
friskby-0.72.2.dist-info/metadata.json
friskby-0.72.2.dist-info/WHEEL
friskby-0.72.2.dist-info/RECORD
