Metadata-Version: 2.0
Name: friskby
Version: 0.72.2
Summary: The friskby module
Home-page: http://github.com/FriskbyBergen/python-friskby
Author: Friskby Bergen
Author-email: pgdr@statoil.com
License: GNU General Public License, Version 3
Keywords: friskby bergen frisk by python-friskby a-small-code air
Platform: UNKNOWN
Requires-Dist: requests
Requires-Dist: pyserial
Requires-Dist: python-dateutil
Requires-Dist: pip
